[
        {
            "eventId": "39e85ed1-c466-4557-98dd-386edc0edf52",
            "eventType": "GameScheduled",
            "data": {
                "date": "2016-01-08",
                "time": "20:00",
                "type": "regular",
                "homeaway": "away",
                "opponent": "cougars",
                "arena": "ma"
            }
        },   
        {
            "eventId": "27cae46d-a2bf-4b77-8a84-529d26aca82a",
            "eventType": "GameStarted",
            "data": {
                "date": "2016-01-08",
                "time": "20:00"
            }
        },   
        {
            "eventId": "db19825d-1836-422a-8d97-62f6cf274e29",
            "eventType": "PenaltyTaken",
            "data": {
                "period": "1",
                "time": "15:42",
                "player": "6",
                "offense": "Head Contact",
                "min": "4",
                "off": "15:42",
                "on": "11:42"
            }
        },   
        {
            "eventId": "3c8fabef-ed76-4e7d-8b65-edbb23c7a2da",
            "eventType": "OpponentPenaltyTaken",
            "data": {
                "period": "1",
                "time": "8:49",
                "player": "9",
                "offense": "Hooking",
                "min": "2",
                "off": "8:49",
                "on": "6:49"
            }
        }, 
        {
            "eventId": "3d65cc9c-b75d-4166-9fce-af998b8272bd",
            "eventType": "OpponentPenaltyTaken",
            "data": {
                "period": "1",
                "time": "4:47",
                "player": "2",
                "offense": "Head Contact",
                "min": "2",
                "off": "4:47",
                "on": "3:24"
            }
        },                         
        {
            "eventId": "3e529262-3c5f-463b-9a0f-201839e4434b",
            "eventType": "GoalScored",
            "data": {
                "period": "1",
                "time": "3:24",
                "kind": "pp",
                "score": "6",
                "assist1": "12",
                "assist2": ""
            }
        },    
        {
            "eventId": "49ff5ca1-c211-4eb3-bd07-c0a3329543f2",
            "eventType": "PenaltyTaken",
            "data": {
                "period": "1",
                "time": "1:37",
                "player": "10",
                "offense": "Hooking",
                "min": "2",
                "off": "1:49",
                "on": ""
            }
        },          
        {
            "eventId": "d63ed0e5-7858-4650-a2a7-cc30aca8c73d",
            "eventType": "OpponentPenaltyTaken",
            "data": {
                "period": "1",
                "time": "19:18",
                "player": "12",
                "offense": "Head Contact",
                "min": "2",
                "off": "19:18",
                "on": "17:18"
            }
        },          
        {
            "eventId": "306c1351-c99e-4d20-a34b-5bf5bc539aac",
            "eventType": "GoalScored",
            "data": {
                "period": "2",
                "time": "14:39",
                "kind": "even",
                "score": "14",
                "assist1": "7",
                "assist2": ""
            }
        }, 
        {
            "eventId": "e61e2d89-e65d-4e53-a37f-08b94cb4ca0e",
            "eventType": "OpponentPenaltyTaken",
            "data": {
                "period": "2",
                "time": "3:51",
                "player": "18",
                "offense": "Head Contact",
                "min": "2",
                "off": "3:51",
                "on": "1:51"
            }
        },      
        {
            "eventId": "d1b0a657-aae1-4dc9-ba10-b879f70085b4",
            "eventType": "OpponentPenaltyTaken",
            "data": {
                "period": "2",
                "time": "2:40",
                "player": "14",
                "offense": "Hooking",
                "min": "2",
                "off": "2:40",
                "on": "0:40"
            }
        },              
        {
            "eventId": "cbfc5ec5-1961-41b9-b5de-943c712a5839",
            "eventType": "GoalScored",
            "data": {
                "period": "3",
                "time": "18:11",
                "kind": "even",
                "score": "9",
                "assist1": "19",
                "assist2": "16"
            }
        }, 
        {
            "eventId": "f3b18a29-84a5-4a51-bca2-6432e5400fee",
            "eventType": "GoalScored",
            "data": {
                "period": "3",
                "time": "15:53",
                "kind": "even",
                "score": "10",
                "assist1": "16",
                "assist2": ""
            }
        },    
        {
            "eventId": "6c25e40e-1753-4d4e-b777-cf9d34a2fad0",
            "eventType": "OpponentPenaltyTaken",
            "data": {
                "period": "3",
                "time": "10:49",
                "player": "10",
                "offense": "Slashing",
                "min": "2",
                "off": "10:49",
                "on": "8:49"
            }
        },   
        {
            "eventId": "b8fc0530-1e55-4ae6-9d6e-ba80a33440b4",
            "eventType": "OpponentPenaltyTaken",
            "data": {
                "period": "3",
                "time": "10:11",
                "player": "9",
                "offense": "Head Contact",
                "min": "4",
                "off": "10:11",
                "on": "6:11"
            }
        },      
        {
            "eventId": "3d03c2f1-8641-482b-9f88-ea70ddea23d2",
            "eventType": "GoalScored",
            "data": {
                "period": "3",
                "time": "6:04",
                "kind": "even",
                "score": "12",
                "assist1": "",
                "assist2": ""
            }
        },            
        {
            "eventId": "af728837-a1a6-4146-a311-72def257b1a4",
            "eventType": "PenaltyTaken",
            "data": {
                "period": "3",
                "time": "2:20",
                "player": "5",
                "offense": "Tripping",
                "min": "2",
                "off": "2:20",
                "on": "0:20"
            }
        },                     
        {
            "eventId": "a18863b4-79db-4fae-a983-68bffaeda9d9",
            "eventType": "GameEnded",
            "data": {
                "date": "2016-01-08",
                "time": "21:45"
            }
        }
]
